setup.py
kedaofx/Show.py
kedaofx/__init__.py
kedaofx/data_manage.py
kedaofx/sql_concat.py
kedaofx.egg-info/PKG-INFO
kedaofx.egg-info/SOURCES.txt
kedaofx.egg-info/dependency_links.txt
kedaofx.egg-info/top_level.txt