Metadata-Version: 2.1
Name: kedaofx
Version: 5.3
Summary: 用作数据分析的便捷指令
Home-page: UNKNOWN
Author: lyr
Author-email: lhx17614480838@163.com
License: UNKNOWN
Platform: UNKNOWN
